pyfilon-1.3.0.dist-info/METADATA
pyfilon-1.3.0.dist-info/WHEEL
pyfilon/__init__.py
pyfilon/filon.py
pyfilon/pyfilon.cpython-311-x86_64-linux-gnu.so
pyfilon-1.3.0.dist-info/RECORD
